mangopy/SiteInformation.csv
mangopy/__init__.py
mangopy/mango.py
mangopy/mosaic.py
mangopy-1.0.1.dist-info/LICENSE
mangopy-1.0.1.dist-info/METADATA
mangopy-1.0.1.dist-info/WHEEL
mangopy-1.0.1.dist-info/top_level.txt
mangopy-1.0.1.dist-info/RECORD
