Metadata-Version: 2.1
Name: mangopy
Version: 1.0.1
Summary: Software for MANGO ASI network
Home-page: UNKNOWN
Author: P. Venkatraman, L. Lamarche, A. Bhatt
License: GPLv3
Platform: UNKNOWN
License-File: LICENSE
Requires-Dist: scipy (>=1.2)
Requires-Dist: h5py (>=2.9)
Requires-Dist: matplotlib (>=2.2.4)
